{
    "flowbite-kbd": {
        "scope": "html",
        "prefix": "flowbite-kbd",
        "body": [
            "<kbd class=\"px-2 py-1.5 text-xs font-semibold text-gray-800 bg-gray-100 border border-gray-200 rounded-lg dark:bg-gray-600 dark:text-gray-100 dark:border-gray-500\">Shift</kbd>"
        ],
        "description": "Flowbite KBD"
    },
    "flowbite-kbd-inside-text": {
        "scope": "html",
        "prefix": "flowbite-kbd-inside-text",
        "body": [
            "<p class=\"text-gray-500 dark:text-gray-400\">",
            "\tPlease press <kbd class=\"px-2 py-1.5 text-xs font-semibold text-gray-800 bg-gray-100 border border-gray-200 rounded-lg dark:bg-gray-600 dark:text-gray-100 dark:border-gray-500\">Ctrl</kbd> + <kbd class=\"px-2 py-1.5 text-xs font-semibold text-gray-800 bg-gray-100 border border-gray-200 rounded-lg dark:bg-gray-600 dark:text-gray-100 dark:border-gray-500\">Shift</kbd> + <kbd class=\"px-2 py-1.5 text-xs font-semibold text-gray-800 bg-gray-100 border border-gray-200 rounded-lg dark:bg-gray-600 dark:text-gray-100 dark:border-gray-500\">R</kbd> to re-render an MDN page.",
            "</p>"
        ],
        "description": "Flowbite KBD inside text"
    },
    "flowbite-kbd-arrow-keys": {
        "scope": "html",
        "prefix": "flowbite-kbd-arrow-keys",
        "body": [
            "<kbd class=\"inline-flex items-center px-2 py-1.5 text-gray-800 bg-gray-100 border border-gray-200 rounded-lg dark:bg-gray-600 dark:text-gray-100 dark:border-gray-500\">",
            "\t<svg class=\"w-4 h-4\" aria-hidden=\"true\" fill=\"currentColor\" xmlns=\"http://www.w3.org/2000/svg\" viewBox=\"0 0 320 512\"><path d=\"M9.39 265.4l127.1-128C143.6 131.1 151.8 128 160 128s16.38 3.125 22.63 9.375l127.1 128c9.156 9.156 11.9 22.91 6.943 34.88S300.9 320 287.1 320H32.01c-12.94 0-24.62-7.781-29.58-19.75S.2333 274.5 9.39 265.4z\"/></svg>",
            "\t<span class=\"sr-only\">Arrow key up</span>",
            "</kbd>",
            "<kbd class=\"inline-flex items-center px-2 py-1.5 text-gray-800 bg-gray-100 border border-gray-200 rounded-lg dark:bg-gray-600 dark:text-gray-100 dark:border-gray-500\">",
            "\t<svg class=\"w-4 h-4\" aria-hidden=\"true\" fill=\"currentColor\" xmlns=\"http://www.w3.org/2000/svg\" viewBox=\"0 0 320 512\"><path d=\"M310.6 246.6l-127.1 128C176.4 380.9 168.2 384 160 384s-16.38-3.125-22.63-9.375l-127.1-128C.2244 237.5-2.516 223.7 2.438 211.8S19.07 192 32 192h255.1c12.94 0 24.62 7.781 29.58 19.75S319.8 237.5 310.6 246.6z\"/></svg>",
            "\t<span class=\"sr-only\">Arrow key down</span>",
            "</kbd>",
            "<kbd class=\"inline-flex items-center px-2 py-1.5 text-gray-800 bg-gray-100 border border-gray-200 rounded-lg dark:bg-gray-600 dark:text-gray-100 dark:border-gray-500\">",
            "\t<svg class=\"w-4 h-4\" aria-hidden=\"true\" fill=\"currentColor\" xmlns=\"http://www.w3.org/2000/svg\" viewBox=\"0 0 256 512\"><path d=\"M137.4 406.6l-128-127.1C3.125 272.4 0 264.2 0 255.1s3.125-16.38 9.375-22.63l128-127.1c9.156-9.156 22.91-11.9 34.88-6.943S192 115.1 192 128v255.1c0 12.94-7.781 24.62-19.75 29.58S146.5 415.8 137.4 406.6z\"/></svg>",
            "\t<span class=\"sr-only\">Arrow key left</span>",
            "</kbd>",
            "<kbd class=\"inline-flex items-center px-2 py-1.5 text-gray-800 bg-gray-100 border border-gray-200 rounded-lg dark:bg-gray-600 dark:text-gray-100 dark:border-gray-500\">",
            "\t<svg class=\"w-4 h-4\" aria-hidden=\"true\" fill=\"currentColor\" xmlns=\"http://www.w3.org/2000/svg\" viewBox=\"0 0 256 512\"><path d=\"M118.6 105.4l128 127.1C252.9 239.6 256 247.8 256 255.1s-3.125 16.38-9.375 22.63l-128 127.1c-9.156 9.156-22.91 11.9-34.88 6.943S64 396.9 64 383.1V128c0-12.94 7.781-24.62 19.75-29.58S109.5 96.23 118.6 105.4z\"/></svg>",
            "\t<span class=\"sr-only\">Arrow key right</span>",
            "</kbd>"
        ],
        "description": "Flowbite KBD arrow keys"
    },
    "flowbite-kbd-inside-table": {
        "scope": "html",
        "prefix": "flowbite-kbd-inside-table",
        "body": [
            "<div class=\"relative overflow-x-auto\">",
            "\t<table class=\"w-full text-sm text-left text-gray-500 dark:text-gray-400\">",
            "\t\t<thead class=\"text-xs text-gray-700 uppercase bg-gray-50 dark:bg-gray-800 dark:text-gray-400\">",
            "\t\t\t<tr>",
            "\t\t\t\t<th scope=\"col\" class=\"px-6 py-3\">",
            "\t\t\t\t\tKey",
            "\t\t\t\t</th>",
            "\t\t\t\t<th scope=\"col\" class=\"px-6 py-3\">",
            "\t\t\t\t\tDescription",
            "\t\t\t\t</th>",
            "\t\t\t</tr>",
            "\t\t</thead>",
            "\t\t<tbody>",
            "\t\t\t<tr class=\"bg-white border-b dark:bg-gray-900 dark:border-gray-700\">",
            "\t\t\t\t<th scope=\"row\" class=\"px-6 py-4 font-medium text-gray-500 whitespace-nowrap dark:text-gray-400\">",
            "\t\t\t\t\t<kbd class=\"px-2 py-1.5 text-xs font-semibold text-gray-800 bg-gray-100 border border-gray-200 rounded-lg dark:bg-gray-600 dark:text-gray-100 dark:border-gray-500\">Shift</kbd>",
            "\t\t\t\t\t\t<span class=\"mx-2\">or</span>",
            "\t\t\t\t\t<kbd class=\"px-2 py-1.5 text-xs font-semibold text-gray-800 bg-gray-100 border border-gray-200 rounded-lg dark:bg-gray-600 dark:text-gray-100 dark:border-gray-500\">Tab</kbd>",
            "\t\t\t\t</th>",
            "\t\t\t\t<td class=\"px-6 py-4\">",
            "\t\t\t\t\tNavigate to interactive elements",
            "\t\t\t\t</td>",
            "\t\t\t</tr>",
            "\t\t\t<tr class=\"bg-white border-b dark:bg-gray-900 dark:border-gray-700\">",
            "\t\t\t\t<th scope=\"row\" class=\"px-6 py-4 font-medium text-gray-500 whitespace-nowrap dark:text-gray-400\">",
            "\t\t\t\t\t<kbd class=\"px-2 py-1.5 text-xs font-semibold text-gray-800 bg-gray-100 border border-gray-200 rounded-lg dark:bg-gray-600 dark:text-gray-100 dark:border-gray-500\">Enter</kbd>",
            "\t\t\t\t\t<span class=\"mx-2\">or</span>",
            "\t\t\t\t\t<kbd class=\"px-4 py-1.5 text-xs font-semibold text-gray-800 bg-gray-100 border border-gray-200 rounded-lg dark:bg-gray-600 dark:text-gray-100 dark:border-gray-500\">Spacebar</kbd>",
            "\t\t\t\t</th>",
            "\t\t\t\t<td class=\"px-6 py-4\">",
            "\t\t\t\t\tEnsure elements with ARIA role=\"button\" can be activated with both key commands.",
            "\t\t\t\t</td>",
            "\t\t\t</tr>",
            "\t\t\t<tr class=\"bg-white dark:bg-gray-900\">",
            "\t\t\t\t<th scope=\"row\" class=\"inline-flex items-center px-6 py-4 font-medium text-gray-500 dark:text-gray-400 whitespace-nowra\">",
            "\t\t\t\t\t<kbd class=\"inline-flex items-center mr-1 px-2 py-1.5 text-gray-800 bg-gray-100 border border-gray-200 rounded-lg dark:bg-gray-600 dark:text-gray-100 dark:border-gray-500\">",
            "\t\t\t\t\t\t<svg class=\"w-4 h-4\" aria-hidden=\"true\" fill=\"currentColor\" xmlns=\"http://www.w3.org/2000/svg\" viewBox=\"0 0 320 512\"><path d=\"M9.39 265.4l127.1-128C143.6 131.1 151.8 128 160 128s16.38 3.125 22.63 9.375l127.1 128c9.156 9.156 11.9 22.91 6.943 34.88S300.9 320 287.1 320H32.01c-12.94 0-24.62-7.781-29.58-19.75S.2333 274.5 9.39 265.4z\"/></svg>",
            "\t\t\t\t\t\t<span class=\"sr-only\">Arrow key up</span>",
            "\t\t\t\t\t</kbd>",
            "\t\t\t\t\t<kbd class=\"inline-flex items-center px-2 py-1.5 text-gray-800 bg-gray-100 border border-gray-200 rounded-lg dark:bg-gray-600 dark:text-gray-100 dark:border-gray-500\">",
            "\t\t\t\t\t\t<svg class=\"w-4 h-4\" aria-hidden=\"true\" fill=\"currentColor\" xmlns=\"http://www.w3.org/2000/svg\" viewBox=\"0 0 320 512\"><path d=\"M310.6 246.6l-127.1 128C176.4 380.9 168.2 384 160 384s-16.38-3.125-22.63-9.375l-127.1-128C.2244 237.5-2.516 223.7 2.438 211.8S19.07 192 32 192h255.1c12.94 0 24.62 7.781 29.58 19.75S319.8 237.5 310.6 246.6z\"/></svg>",
            "\t\t\t\t\t\t<span class=\"sr-only\">Arrow key down</span>",
            "\t\t\t\t\t</kbd>",
            "\t\t\t\t\t<span class=\"mx-2\">or</span>",
            "\t\t\t\t\t<kbd class=\"inline-flex items-center mr-1 px-2 py-1.5 text-gray-800 bg-gray-100 border border-gray-200 rounded-lg dark:bg-gray-600 dark:text-gray-100 dark:border-gray-500\">",
            "\t\t\t\t\t\t<svg class=\"w-4 h-4\" aria-hidden=\"true\" fill=\"currentColor\" xmlns=\"http://www.w3.org/2000/svg\" viewBox=\"0 0 256 512\"><path d=\"M137.4 406.6l-128-127.1C3.125 272.4 0 264.2 0 255.1s3.125-16.38 9.375-22.63l128-127.1c9.156-9.156 22.91-11.9 34.88-6.943S192 115.1 192 128v255.1c0 12.94-7.781 24.62-19.75 29.58S146.5 415.8 137.4 406.6z\"/></svg>",
            "\t\t\t\t\t\t<span class=\"sr-only\">Arrow key left</span>",
            "\t\t\t\t\t</kbd>",
            "\t\t\t\t\t<kbd class=\"inline-flex items-center px-2 py-1.5 text-gray-800 bg-gray-100 border border-gray-200 rounded-lg dark:bg-gray-600 dark:text-gray-100 dark:border-gray-500\">",
            "\t\t\t\t\t\t<svg class=\"w-4 h-4\" aria-hidden=\"true\" fill=\"currentColor\" xmlns=\"http://www.w3.org/2000/svg\" viewBox=\"0 0 256 512\"><path d=\"M118.6 105.4l128 127.1C252.9 239.6 256 247.8 256 255.1s-3.125 16.38-9.375 22.63l-128 127.1c-9.156 9.156-22.91 11.9-34.88 6.943S64 396.9 64 383.1V128c0-12.94 7.781-24.62 19.75-29.58S109.5 96.23 118.6 105.4z\"/></svg>",
            "\t\t\t\t\t\t<span class=\"sr-only\">Arrow key right</span>",
            "\t\t\t\t\t</kbd>",
            "\t\t\t\t</th>",
            "\t\t\t\t<td class=\"px-6 py-4\">",
            "\t\t\t\t\tChoose and activate previous/next tab.",
            "\t\t\t\t</td>",
            "\t\t\t</tr>",
            "\t\t</tbody>",
            "\t</table>",
            "</div>"
        ],
        "description": "Flowbite KBD inside table"
    }
}